zumi/__init__.py
zumi/personality.py
zumi/protocol.py
zumi/zumi.py
zumi/util/Century Gothic.ttf
zumi/util/__init__.py
zumi/util/camera.py
zumi/util/color_classifier.py
zumi/util/dice.py
zumi/util/futura.ttf
zumi/util/gyro_draw.py
zumi/util/hand_drawing_classifier.py
zumi/util/image_processor.py
zumi/util/knn_classifier.py
zumi/util/line_tracer.py
zumi/util/maze.py
zumi/util/screen.py
zumi/util/tourist_demo_helper.py
zumi/util/vision.py
zumi/util/images/angry.ppm
zumi/util/images/battery_charging.ppm
zumi/util/images/battery_empty.ppm
zumi/util/images/battery_emptycharging.ppm
zumi/util/images/big_eyes1.ppm
zumi/util/images/big_eyes2.ppm
zumi/util/images/big_eyes3.ppm
zumi/util/images/blankbar.ppm
zumi/util/images/calibrated.ppm
zumi/util/images/calibrating.ppm
zumi/util/images/calibrating1.ppm
zumi/util/images/calibrating2.ppm
zumi/util/images/calibrating_new.ppm
zumi/util/images/close.ppm
zumi/util/images/connected.ppm
zumi/util/images/disoriented.ppm
zumi/util/images/focus.ppm
zumi/util/images/foundme.ppm
zumi/util/images/getting_online.ppm
zumi/util/images/happy1.ppm
zumi/util/images/happy_1.ppm
zumi/util/images/happy_left1.ppm
zumi/util/images/happy_left2.ppm
zumi/util/images/happy_right1.ppm
zumi/util/images/happy_right2.ppm
zumi/util/images/im_online.ppm
zumi/util/images/loading.ppm
zumi/util/images/lookleft1.ppm
zumi/util/images/lookleft2.ppm
zumi/util/images/lookright1.ppm
zumi/util/images/lookright2.ppm
zumi/util/images/neutral1.ppm
zumi/util/images/neutral2.ppm
zumi/util/images/neutral3.ppm
zumi/util/images/onlinefail.ppm
zumi/util/images/opening_1.ppm
zumi/util/images/sad1.ppm
zumi/util/images/sad2.ppm
zumi/util/images/sad3.ppm
zumi/util/images/shock1.ppm
zumi/util/images/shock2.ppm
zumi/util/images/sleep.ppm
zumi/util/images/sleep2.ppm
zumi/util/images/sleep_z1.ppm
zumi/util/images/sleep_z2.ppm
zumi/util/images/sleep_z3.ppm
zumi/util/images/sleepy_loading.ppm
zumi-1.66.dist-info/DESCRIPTION.rst
zumi-1.66.dist-info/METADATA
zumi-1.66.dist-info/RECORD
zumi-1.66.dist-info/WHEEL
zumi-1.66.dist-info/metadata.json
zumi-1.66.dist-info/top_level.txt
