Metadata-Version: 2.0
Name: zumi
Version: 1.66
Summary: Python Library for Zumi. Only working on rasbian
Home-page: UNKNOWN
Author: Robolink
Author-email: info@robolink.com
License: UNKNOWN
Keywords: robolink,zumi
Platform: UNKNOWN
Requires-Python: >=3.3
Requires-Dist: pyzbar
Requires-Dist: smbus2
